client/__init__.py
client/client.py
client/client_app/__init__.py
client/client_app/client_utils.py
client/client_app/core.py
client/client_app/models.py
client/client_app/gui/__init__.py
client/client_app/gui/client_window.py
client/client_app/gui/ui_client.py
client/client_app/gui/welcome.py
client/config/__init__.py
client/config/settigs.py
client/config/utils.py
client/log/__init__.py
client/log/settings/__init__.py
client/log/settings/client_log_config.py
client/log/settings/decor_log_config.py
client/log/settings/server_log_config.py
devChat_client-0.1.0.dist-info/METADATA
devChat_client-0.1.0.dist-info/WHEEL
devChat_client-0.1.0.dist-info/top_level.txt
devChat_client-0.1.0.dist-info/RECORD
